pypod/__init__.py
pypod/app.py
pypod/cli.py
pypod/config.py
pypod/player.py
pypod/song.py
pypod/style.css
pypod/ui.py
pypod/utils.py
python_pod-0.1.2.dist-info/entry_points.txt
python_pod-0.1.2.dist-info/WHEEL
python_pod-0.1.2.dist-info/METADATA
python_pod-0.1.2.dist-info/RECORD
