Metadata-Version: 2.1
Name: python-pod
Version: 0.1.2
Summary: Python terminal music player
License: MIT
Author: Misha Behersky
Author-email: bmwant@gmail.com
Requires-Python: >=3.8.1,<4.0.0
Classifier: License :: OSI Approved :: MIT License
Classifier: Programming Language :: Python :: 3
Classifier: Programming Language :: Python :: 3.9
Classifier: Programming Language :: Python :: 3.10
Requires-Dist: click (>=8.1.3,<9.0.0)
Requires-Dist: pyaudio (>=0.2.12,<0.3.0)
Requires-Dist: rich (>=13.0.0,<14.0.0)
Requires-Dist: textual (>=0.9.1,<0.10.0)
